{
    "eggcartons.py": [
        {
            "operation": "TYPED",
            "lines": 0,
            "keyStrokeTimeStamp": "Tue Jul 13 2021 15:19:07",
            "keyStrokeInfo": "\r\n\t",
            "position": "8,23"
        },
        {
            "operation": "TYPED",
            "lines": 0,
            "keyStrokeTimeStamp": "Tue Jul 13 2021 15:19:09",
            "keyStrokeInfo": "e",
            "position": "9,2"
        },
        {
            "operation": "TYPED",
            "lines": 0,
            "keyStrokeTimeStamp": "Tue Jul 13 2021 15:19:09",
            "keyStrokeInfo": "g",
            "position": "9,3"
        },
        {
            "operation": "TYPED",
            "lines": 0,
            "keyStrokeTimeStamp": "Tue Jul 13 2021 15:19:09",
            "keyStrokeInfo": "g",
            "position": "9,4"
        },
        {
            "operation": "TYPED",
            "lines": 0,
            "keyStrokeTimeStamp": "Tue Jul 13 2021 15:19:09",
            "keyStrokeInfo": "s",
            "position": "9,5"
        },
        {
            "operation": "TYPED",
            "lines": 0,
            "keyStrokeTimeStamp": "Tue Jul 13 2021 15:19:10",
            "keyStrokeInfo": "=",
            "position": "9,6"
        },
        {
            "operation": "TYPED",
            "lines": 0,
            "keyStrokeTimeStamp": "Tue Jul 13 2021 15:19:10",
            "keyStrokeInfo": "a",
            "position": "9,7"
        },
        {
            "operation": "TYPED",
            "lines": 0,
            "keyStrokeTimeStamp": "Tue Jul 13 2021 15:19:11",
            "keyStrokeInfo": "b",
            "position": "9,8"
        },
        {
            "operation": "TYPED",
            "lines": 0,
            "keyStrokeTimeStamp": "Tue Jul 13 2021 15:19:11",
            "keyStrokeInfo": "s",
            "position": "9,9"
        },
        {
            "operation": "TYPED",
            "lines": 0,
            "keyStrokeTimeStamp": "Tue Jul 13 2021 15:19:11",
            "keyStrokeInfo": "()",
            "position": "9,10"
        },
        {
            "operation": "TYPED",
            "lines": 0,
            "keyStrokeTimeStamp": "Tue Jul 13 2021 15:19:12",
            "keyStrokeInfo": "a",
            "position": "9,11"
        },
        {
            "operation": "DELETE",
            "lines": 0,
            "keyStrokeTimeStamp": "Tue Jul 13 2021 15:19:12",
            "keyStrokeInfo": "",
            "position": "9,11"
        },
        {
            "operation": "TYPED",
            "lines": 0,
            "keyStrokeTimeStamp": "Tue Jul 13 2021 15:19:13",
            "keyStrokeInfo": "e",
            "position": "9,11"
        },
        {
            "operation": "TYPED",
            "lines": 0,
            "keyStrokeTimeStamp": "Tue Jul 13 2021 15:19:13",
            "keyStrokeInfo": "g",
            "position": "9,12"
        },
        {
            "operation": "TYPED",
            "lines": 0,
            "keyStrokeTimeStamp": "Tue Jul 13 2021 15:19:13",
            "keyStrokeInfo": "g",
            "position": "9,13"
        },
        {
            "operation": "TYPED",
            "lines": 0,
            "keyStrokeTimeStamp": "Tue Jul 13 2021 15:19:13",
            "keyStrokeInfo": "s",
            "position": "9,14"
        },
        {
            "operation": "TYPED",
            "lines": 0,
            "keyStrokeTimeStamp": "Tue Jul 13 2021 15:19:15",
            "keyStrokeInfo": "\r\n\t",
            "position": "9,16"
        },
        {
            "operation": "TYPED",
            "lines": 0,
            "keyStrokeTimeStamp": "Tue Jul 13 2021 15:19:33",
            "keyStrokeInfo": "i",
            "position": "10,2"
        },
        {
            "operation": "TYPED",
            "lines": 0,
            "keyStrokeTimeStamp": "Tue Jul 13 2021 15:19:33",
            "keyStrokeInfo": "f",
            "position": "10,3"
        },
        {
            "operation": "TYPED",
            "lines": 0,
            "keyStrokeTimeStamp": "Tue Jul 13 2021 15:19:33",
            "keyStrokeInfo": " ",
            "position": "10,4"
        },
        {
            "operation": "TYPED",
            "lines": 0,
            "keyStrokeTimeStamp": "Tue Jul 13 2021 15:19:33",
            "keyStrokeInfo": "e",
            "position": "10,5"
        },
        {
            "operation": "TYPED",
            "lines": 0,
            "keyStrokeTimeStamp": "Tue Jul 13 2021 15:19:33",
            "keyStrokeInfo": "g",
            "position": "10,6"
        },
        {
            "operation": "TYPED",
            "lines": 0,
            "keyStrokeTimeStamp": "Tue Jul 13 2021 15:19:33",
            "keyStrokeInfo": "g",
            "position": "10,7"
        },
        {
            "operation": "TYPED",
            "lines": 0,
            "keyStrokeTimeStamp": "Tue Jul 13 2021 15:19:34",
            "keyStrokeInfo": "s",
            "position": "10,8"
        },
        {
            "operation": "TYPED",
            "lines": 0,
            "keyStrokeTimeStamp": "Tue Jul 13 2021 15:19:34",
            "keyStrokeInfo": " ",
            "position": "10,9"
        },
        {
            "operation": "DELETE",
            "lines": 0,
            "keyStrokeTimeStamp": "Tue Jul 13 2021 15:19:35",
            "keyStrokeInfo": "",
            "position": "10,9"
        },
        {
            "operation": "TYPED",
            "lines": 0,
            "keyStrokeTimeStamp": "Tue Jul 13 2021 15:19:37",
            "keyStrokeInfo": ">",
            "position": "10,9"
        },
        {
            "operation": "TYPED",
            "lines": 0,
            "keyStrokeTimeStamp": "Tue Jul 13 2021 15:19:37",
            "keyStrokeInfo": "1",
            "position": "10,10"
        },
        {
            "operation": "TYPED",
            "lines": 0,
            "keyStrokeTimeStamp": "Tue Jul 13 2021 15:19:37",
            "keyStrokeInfo": "2",
            "position": "10,11"
        },
        {
            "operation": "TYPED",
            "lines": 0,
            "keyStrokeTimeStamp": "Tue Jul 13 2021 15:19:38",
            "keyStrokeInfo": " ",
            "position": "10,12"
        },
        {
            "operation": "DELETE",
            "lines": 0,
            "keyStrokeTimeStamp": "Tue Jul 13 2021 15:19:39",
            "keyStrokeInfo": "",
            "position": "10,12"
        },
        {
            "operation": "TYPED",
            "lines": 0,
            "keyStrokeTimeStamp": "Tue Jul 13 2021 15:19:39",
            "keyStrokeInfo": ":",
            "position": "10,12"
        },
        {
            "operation": "TYPED",
            "lines": 0,
            "keyStrokeTimeStamp": "Tue Jul 13 2021 15:19:40",
            "keyStrokeInfo": "\r\n\t\t",
            "position": "10,13"
        },
        {
            "operation": "DELETE",
            "lines": 0,
            "keyStrokeTimeStamp": "Tue Jul 13 2021 15:19:42",
            "keyStrokeInfo": "\r\n\t",
            "position": "9,16"
        },
        {
            "operation": "TYPED",
            "lines": 0,
            "keyStrokeTimeStamp": "Tue Jul 13 2021 15:19:44",
            "keyStrokeInfo": "c",
            "position": "10,2"
        },
        {
            "operation": "TYPED",
            "lines": 0,
            "keyStrokeTimeStamp": "Tue Jul 13 2021 15:19:44",
            "keyStrokeInfo": "o",
            "position": "10,3"
        },
        {
            "operation": "TYPED",
            "lines": 0,
            "keyStrokeTimeStamp": "Tue Jul 13 2021 15:19:44",
            "keyStrokeInfo": "u",
            "position": "10,4"
        },
        {
            "operation": "TYPED",
            "lines": 0,
            "keyStrokeTimeStamp": "Tue Jul 13 2021 15:19:44",
            "keyStrokeInfo": "n",
            "position": "10,5"
        },
        {
            "operation": "TYPED",
            "lines": 0,
            "keyStrokeTimeStamp": "Tue Jul 13 2021 15:19:44",
            "keyStrokeInfo": "t",
            "position": "10,6"
        },
        {
            "operation": "TYPED",
            "lines": 0,
            "keyStrokeTimeStamp": "Tue Jul 13 2021 15:19:45",
            "keyStrokeInfo": "=",
            "position": "10,7"
        },
        {
            "operation": "TYPED",
            "lines": 0,
            "keyStrokeTimeStamp": "Tue Jul 13 2021 15:19:48",
            "keyStrokeInfo": "1",
            "position": "10,8"
        },
        {
            "operation": "TYPED",
            "lines": 0,
            "keyStrokeTimeStamp": "Tue Jul 13 2021 15:19:51",
            "keyStrokeInfo": "\r\n\t\t",
            "position": "11,13"
        },
        {
            "operation": "TYPED",
            "lines": 0,
            "keyStrokeTimeStamp": "Tue Jul 13 2021 15:19:52",
            "keyStrokeInfo": "c",
            "position": "12,3"
        },
        {
            "operation": "TYPED",
            "lines": 0,
            "keyStrokeTimeStamp": "Tue Jul 13 2021 15:19:52",
            "keyStrokeInfo": "o",
            "position": "12,4"
        },
        {
            "operation": "TYPED",
            "lines": 0,
            "keyStrokeTimeStamp": "Tue Jul 13 2021 15:19:53",
            "keyStrokeInfo": "u",
            "position": "12,5"
        },
        {
            "operation": "TYPED",
            "lines": 0,
            "keyStrokeTimeStamp": "Tue Jul 13 2021 15:19:53",
            "keyStrokeInfo": "n",
            "position": "12,6"
        },
        {
            "operation": "TYPED",
            "lines": 0,
            "keyStrokeTimeStamp": "Tue Jul 13 2021 15:19:53",
            "keyStrokeInfo": "t",
            "position": "12,7"
        },
        {
            "operation": "TYPED",
            "lines": 0,
            "keyStrokeTimeStamp": "Tue Jul 13 2021 15:19:54",
            "keyStrokeInfo": "+",
            "position": "12,8"
        },
        {
            "operation": "TYPED",
            "lines": 0,
            "keyStrokeTimeStamp": "Tue Jul 13 2021 15:19:54",
            "keyStrokeInfo": "=",
            "position": "12,9"
        },
        {
            "operation": "TYPED",
            "lines": 0,
            "keyStrokeTimeStamp": "Tue Jul 13 2021 15:19:55",
            "keyStrokeInfo": "1",
            "position": "12,10"
        },
        {
            "operation": "TYPED",
            "lines": 0,
            "keyStrokeTimeStamp": "Tue Jul 13 2021 15:19:55",
            "keyStrokeInfo": "\r\n\t\t",
            "position": "12,11"
        },
        {
            "operation": "DELETE",
            "lines": 0,
            "keyStrokeTimeStamp": "Tue Jul 13 2021 15:19:59",
            "keyStrokeInfo": "",
            "position": "13,1"
        },
        {
            "operation": "TYPED",
            "lines": 0,
            "keyStrokeTimeStamp": "Tue Jul 13 2021 15:20:00",
            "keyStrokeInfo": "c",
            "position": "15,9"
        },
        {
            "operation": "TYPED",
            "lines": 0,
            "keyStrokeTimeStamp": "Tue Jul 13 2021 15:20:00",
            "keyStrokeInfo": "o",
            "position": "15,10"
        },
        {
            "operation": "TYPED",
            "lines": 0,
            "keyStrokeTimeStamp": "Tue Jul 13 2021 15:20:00",
            "keyStrokeInfo": "u",
            "position": "15,11"
        },
        {
            "operation": "TYPED",
            "lines": 0,
            "keyStrokeTimeStamp": "Tue Jul 13 2021 15:20:00",
            "keyStrokeInfo": "n",
            "position": "15,12"
        },
        {
            "operation": "TYPED",
            "lines": 0,
            "keyStrokeTimeStamp": "Tue Jul 13 2021 15:20:01",
            "keyStrokeInfo": "t",
            "position": "15,13"
        },
        {
            "operation": "TYPED",
            "lines": 0,
            "keyStrokeTimeStamp": "Tue Jul 13 2021 15:20:04",
            "keyStrokeInfo": "\r\n\t",
            "position": "9,16"
        },
        {
            "operation": "TYPED",
            "lines": 0,
            "keyStrokeTimeStamp": "Tue Jul 13 2021 15:20:05",
            "keyStrokeInfo": "i",
            "position": "10,2"
        },
        {
            "operation": "TYPED",
            "lines": 0,
            "keyStrokeTimeStamp": "Tue Jul 13 2021 15:20:05",
            "keyStrokeInfo": "f",
            "position": "10,3"
        },
        {
            "operation": "TYPED",
            "lines": 0,
            "keyStrokeTimeStamp": "Tue Jul 13 2021 15:20:05",
            "keyStrokeInfo": " ",
            "position": "10,4"
        },
        {
            "operation": "TYPED",
            "lines": 0,
            "keyStrokeTimeStamp": "Tue Jul 13 2021 15:20:06",
            "keyStrokeInfo": "e",
            "position": "10,5"
        },
        {
            "operation": "TYPED",
            "lines": 0,
            "keyStrokeTimeStamp": "Tue Jul 13 2021 15:20:07",
            "keyStrokeInfo": "g",
            "position": "10,6"
        },
        {
            "operation": "TYPED",
            "lines": 0,
            "keyStrokeTimeStamp": "Tue Jul 13 2021 15:20:07",
            "keyStrokeInfo": "g",
            "position": "10,7"
        },
        {
            "operation": "TYPED",
            "lines": 0,
            "keyStrokeTimeStamp": "Tue Jul 13 2021 15:20:07",
            "keyStrokeInfo": "s",
            "position": "10,8"
        },
        {
            "operation": "DELETE",
            "lines": 0,
            "keyStrokeTimeStamp": "Tue Jul 13 2021 15:20:08",
            "keyStrokeInfo": "",
            "position": "10,8"
        },
        {
            "operation": "DELETE",
            "lines": 0,
            "keyStrokeTimeStamp": "Tue Jul 13 2021 15:20:08",
            "keyStrokeInfo": "",
            "position": "10,7"
        },
        {
            "operation": "DELETE",
            "lines": 0,
            "keyStrokeTimeStamp": "Tue Jul 13 2021 15:20:09",
            "keyStrokeInfo": "",
            "position": "10,6"
        },
        {
            "operation": "DELETE",
            "lines": 0,
            "keyStrokeTimeStamp": "Tue Jul 13 2021 15:20:09",
            "keyStrokeInfo": "",
            "position": "10,5"
        },
        {
            "operation": "DELETE",
            "lines": 0,
            "keyStrokeTimeStamp": "Tue Jul 13 2021 15:20:09",
            "keyStrokeInfo": "",
            "position": "10,4"
        },
        {
            "operation": "DELETE",
            "lines": 0,
            "keyStrokeTimeStamp": "Tue Jul 13 2021 15:20:09",
            "keyStrokeInfo": "",
            "position": "10,3"
        },
        {
            "operation": "DELETE",
            "lines": 0,
            "keyStrokeTimeStamp": "Tue Jul 13 2021 15:20:09",
            "keyStrokeInfo": "",
            "position": "10,2"
        },
        {
            "operation": "TYPED",
            "lines": 0,
            "keyStrokeTimeStamp": "Tue Jul 13 2021 15:20:11",
            "keyStrokeInfo": "\r\n\t\t",
            "position": "13,11"
        },
        {
            "operation": "DELETE",
            "lines": 0,
            "keyStrokeTimeStamp": "Tue Jul 13 2021 15:20:12",
            "keyStrokeInfo": "",
            "position": "14,2"
        },
        {
            "operation": "TYPED",
            "lines": 0,
            "keyStrokeTimeStamp": "Tue Jul 13 2021 15:20:12",
            "keyStrokeInfo": "e",
            "position": "14,2"
        },
        {
            "operation": "TYPED",
            "lines": 0,
            "keyStrokeTimeStamp": "Tue Jul 13 2021 15:20:13",
            "keyStrokeInfo": "l",
            "position": "14,3"
        },
        {
            "operation": "TYPED",
            "lines": 0,
            "keyStrokeTimeStamp": "Tue Jul 13 2021 15:20:13",
            "keyStrokeInfo": "s",
            "position": "14,4"
        },
        {
            "operation": "TYPED",
            "lines": 0,
            "keyStrokeTimeStamp": "Tue Jul 13 2021 15:20:13",
            "keyStrokeInfo": "e",
            "position": "14,5"
        },
        {
            "operation": "TYPED",
            "lines": 0,
            "keyStrokeTimeStamp": "Tue Jul 13 2021 15:20:13",
            "keyStrokeInfo": ":",
            "position": "14,6"
        },
        {
            "operation": "TYPED",
            "lines": 0,
            "keyStrokeTimeStamp": "Tue Jul 13 2021 15:20:14",
            "keyStrokeInfo": " ",
            "position": "14,7"
        },
        {
            "operation": "TYPED",
            "lines": 0,
            "keyStrokeTimeStamp": "Tue Jul 13 2021 15:20:14",
            "keyStrokeInfo": "\r\n\t\t",
            "position": "14,8"
        },
        {
            "operation": "TYPED",
            "lines": 0,
            "keyStrokeTimeStamp": "Tue Jul 13 2021 15:20:15",
            "keyStrokeInfo": "r",
            "position": "15,3"
        },
        {
            "operation": "TYPED",
            "lines": 0,
            "keyStrokeTimeStamp": "Tue Jul 13 2021 15:20:15",
            "keyStrokeInfo": "e",
            "position": "15,4"
        },
        {
            "operation": "TYPED",
            "lines": 0,
            "keyStrokeTimeStamp": "Tue Jul 13 2021 15:20:16",
            "keyStrokeInfo": "t",
            "position": "15,5"
        },
        {
            "operation": "TYPED",
            "lines": 0,
            "keyStrokeTimeStamp": "Tue Jul 13 2021 15:20:16",
            "keyStrokeInfo": "u",
            "position": "15,6"
        },
        {
            "operation": "TYPED",
            "lines": 0,
            "keyStrokeTimeStamp": "Tue Jul 13 2021 15:20:16",
            "keyStrokeInfo": "r",
            "position": "15,7"
        },
        {
            "operation": "TYPED",
            "lines": 0,
            "keyStrokeTimeStamp": "Tue Jul 13 2021 15:20:16",
            "keyStrokeInfo": "n",
            "position": "15,8"
        },
        {
            "operation": "TYPED",
            "lines": 0,
            "keyStrokeTimeStamp": "Tue Jul 13 2021 15:20:16",
            "keyStrokeInfo": " ",
            "position": "15,9"
        },
        {
            "operation": "TYPED",
            "lines": 0,
            "keyStrokeTimeStamp": "Tue Jul 13 2021 15:20:17",
            "keyStrokeInfo": "c",
            "position": "15,10"
        },
        {
            "operation": "TYPED",
            "lines": 0,
            "keyStrokeTimeStamp": "Tue Jul 13 2021 15:20:17",
            "keyStrokeInfo": "o",
            "position": "15,11"
        },
        {
            "operation": "TYPED",
            "lines": 0,
            "keyStrokeTimeStamp": "Tue Jul 13 2021 15:20:17",
            "keyStrokeInfo": "u",
            "position": "15,12"
        },
        {
            "operation": "TYPED",
            "lines": 0,
            "keyStrokeTimeStamp": "Tue Jul 13 2021 15:20:17",
            "keyStrokeInfo": "n",
            "position": "15,13"
        },
        {
            "operation": "TYPED",
            "lines": 0,
            "keyStrokeTimeStamp": "Tue Jul 13 2021 15:20:17",
            "keyStrokeInfo": "t",
            "position": "15,14"
        },
        {
            "operation": "DELETE",
            "lines": 0,
            "keyStrokeTimeStamp": "Tue Jul 13 2021 15:20:20",
            "keyStrokeInfo": "",
            "position": "18,13"
        },
        {
            "operation": "DELETE",
            "lines": 0,
            "keyStrokeTimeStamp": "Tue Jul 13 2021 15:20:20",
            "keyStrokeInfo": "",
            "position": "18,12"
        },
        {
            "operation": "DELETE",
            "lines": 0,
            "keyStrokeTimeStamp": "Tue Jul 13 2021 15:20:20",
            "keyStrokeInfo": "",
            "position": "18,11"
        },
        {
            "operation": "DELETE",
            "lines": 0,
            "keyStrokeTimeStamp": "Tue Jul 13 2021 15:20:21",
            "keyStrokeInfo": "",
            "position": "18,10"
        },
        {
            "operation": "DELETE",
            "lines": 0,
            "keyStrokeTimeStamp": "Tue Jul 13 2021 15:20:21",
            "keyStrokeInfo": "",
            "position": "18,9"
        },
        {
            "operation": "DELETE",
            "lines": 0,
            "keyStrokeTimeStamp": "Tue Jul 13 2021 15:20:21",
            "keyStrokeInfo": "",
            "position": "18,8"
        },
        {
            "operation": "DELETE",
            "lines": 0,
            "keyStrokeTimeStamp": "Tue Jul 13 2021 15:20:21",
            "keyStrokeInfo": "",
            "position": "18,7"
        },
        {
            "operation": "DELETE",
            "lines": 0,
            "keyStrokeTimeStamp": "Tue Jul 13 2021 15:20:21",
            "keyStrokeInfo": "",
            "position": "18,6"
        },
        {
            "operation": "DELETE",
            "lines": 0,
            "keyStrokeTimeStamp": "Tue Jul 13 2021 15:20:21",
            "keyStrokeInfo": "",
            "position": "18,5"
        },
        {
            "operation": "DELETE",
            "lines": 0,
            "keyStrokeTimeStamp": "Tue Jul 13 2021 15:20:21",
            "keyStrokeInfo": "",
            "position": "18,4"
        },
        {
            "operation": "DELETE",
            "lines": 0,
            "keyStrokeTimeStamp": "Tue Jul 13 2021 15:20:21",
            "keyStrokeInfo": "",
            "position": "18,3"
        },
        {
            "operation": "DELETE",
            "lines": 0,
            "keyStrokeTimeStamp": "Tue Jul 13 2021 15:20:21",
            "keyStrokeInfo": "",
            "position": "18,2"
        },
        {
            "operation": "DELETE",
            "lines": 0,
            "keyStrokeTimeStamp": "Tue Jul 13 2021 15:20:22",
            "keyStrokeInfo": "",
            "position": "18,1"
        },
        {
            "operation": "DELETE",
            "lines": 1,
            "keyStrokeTimeStamp": "Tue Jul 13 2021 15:20:22",
            "keyStrokeInfo": "",
            "position": "17,1"
        },
        {
            "operation": "DELETE",
            "lines": 1,
            "keyStrokeTimeStamp": "Tue Jul 13 2021 15:20:22",
            "keyStrokeInfo": "",
            "position": "16,1"
        },
        {
            "operation": "DELETE",
            "lines": 1,
            "keyStrokeTimeStamp": "Tue Jul 13 2021 15:20:23",
            "keyStrokeInfo": "",
            "position": "15,15"
        },
        {
            "operation": "TYPED",
            "lines": 0,
            "keyStrokeTimeStamp": "Tue Jul 13 2021 15:20:27",
            "keyStrokeInfo": "\r\n\t\t",
            "position": "13,11"
        },
        {
            "operation": "TYPED",
            "lines": 0,
            "keyStrokeTimeStamp": "Tue Jul 13 2021 15:20:28",
            "keyStrokeInfo": "r",
            "position": "14,3"
        },
        {
            "operation": "TYPED",
            "lines": 0,
            "keyStrokeTimeStamp": "Tue Jul 13 2021 15:20:29",
            "keyStrokeInfo": "e",
            "position": "14,4"
        },
        {
            "operation": "TYPED",
            "lines": 0,
            "keyStrokeTimeStamp": "Tue Jul 13 2021 15:20:29",
            "keyStrokeInfo": "t",
            "position": "14,5"
        },
        {
            "operation": "TYPED",
            "lines": 0,
            "keyStrokeTimeStamp": "Tue Jul 13 2021 15:20:29",
            "keyStrokeInfo": "u",
            "position": "14,6"
        },
        {
            "operation": "TYPED",
            "lines": 0,
            "keyStrokeTimeStamp": "Tue Jul 13 2021 15:20:29",
            "keyStrokeInfo": "r",
            "position": "14,7"
        },
        {
            "operation": "TYPED",
            "lines": 0,
            "keyStrokeTimeStamp": "Tue Jul 13 2021 15:20:29",
            "keyStrokeInfo": "n",
            "position": "14,8"
        },
        {
            "operation": "TYPED",
            "lines": 0,
            "keyStrokeTimeStamp": "Tue Jul 13 2021 15:20:29",
            "keyStrokeInfo": " ",
            "position": "14,9"
        },
        {
            "operation": "TYPED",
            "lines": 0,
            "keyStrokeTimeStamp": "Tue Jul 13 2021 15:20:29",
            "keyStrokeInfo": "c",
            "position": "14,10"
        },
        {
            "operation": "TYPED",
            "lines": 0,
            "keyStrokeTimeStamp": "Tue Jul 13 2021 15:20:30",
            "keyStrokeInfo": "o",
            "position": "14,11"
        },
        {
            "operation": "TYPED",
            "lines": 0,
            "keyStrokeTimeStamp": "Tue Jul 13 2021 15:20:30",
            "keyStrokeInfo": "u",
            "position": "14,12"
        },
        {
            "operation": "TYPED",
            "lines": 0,
            "keyStrokeTimeStamp": "Tue Jul 13 2021 15:20:30",
            "keyStrokeInfo": "n",
            "position": "14,13"
        },
        {
            "operation": "TYPED",
            "lines": 0,
            "keyStrokeTimeStamp": "Tue Jul 13 2021 15:20:30",
            "keyStrokeInfo": "t",
            "position": "14,14"
        },
        {
            "operation": "TYPED",
            "lines": 0,
            "keyStrokeTimeStamp": "Tue Jul 13 2021 15:21:19",
            "keyStrokeInfo": "i",
            "position": "10,2"
        },
        {
            "operation": "TYPED",
            "lines": 0,
            "keyStrokeTimeStamp": "Tue Jul 13 2021 15:21:19",
            "keyStrokeInfo": "f",
            "position": "10,3"
        },
        {
            "operation": "TYPED",
            "lines": 0,
            "keyStrokeTimeStamp": "Tue Jul 13 2021 15:21:20",
            "keyStrokeInfo": " ",
            "position": "10,4"
        },
        {
            "operation": "TYPED",
            "lines": 0,
            "keyStrokeTimeStamp": "Tue Jul 13 2021 15:21:20",
            "keyStrokeInfo": "e",
            "position": "10,5"
        },
        {
            "operation": "TYPED",
            "lines": 0,
            "keyStrokeTimeStamp": "Tue Jul 13 2021 15:21:20",
            "keyStrokeInfo": "h",
            "position": "10,6"
        },
        {
            "operation": "DELETE",
            "lines": 0,
            "keyStrokeTimeStamp": "Tue Jul 13 2021 15:21:20",
            "keyStrokeInfo": "",
            "position": "10,6"
        },
        {
            "operation": "TYPED",
            "lines": 0,
            "keyStrokeTimeStamp": "Tue Jul 13 2021 15:21:21",
            "keyStrokeInfo": "g",
            "position": "10,6"
        },
        {
            "operation": "TYPED",
            "lines": 0,
            "keyStrokeTimeStamp": "Tue Jul 13 2021 15:21:21",
            "keyStrokeInfo": "g",
            "position": "10,7"
        },
        {
            "operation": "TYPED",
            "lines": 0,
            "keyStrokeTimeStamp": "Tue Jul 13 2021 15:21:21",
            "keyStrokeInfo": "s",
            "position": "10,8"
        },
        {
            "operation": "TYPED",
            "lines": 0,
            "keyStrokeTimeStamp": "Tue Jul 13 2021 15:21:22",
            "keyStrokeInfo": "=",
            "position": "10,9"
        },
        {
            "operation": "TYPED",
            "lines": 0,
            "keyStrokeTimeStamp": "Tue Jul 13 2021 15:21:22",
            "keyStrokeInfo": "=",
            "position": "10,10"
        },
        {
            "operation": "TYPED",
            "lines": 0,
            "keyStrokeTimeStamp": "Tue Jul 13 2021 15:21:23",
            "keyStrokeInfo": "0",
            "position": "10,11"
        },
        {
            "operation": "TYPED",
            "lines": 0,
            "keyStrokeTimeStamp": "Tue Jul 13 2021 15:21:24",
            "keyStrokeInfo": ":",
            "position": "10,12"
        },
        {
            "operation": "TYPED",
            "lines": 0,
            "keyStrokeTimeStamp": "Tue Jul 13 2021 15:21:24",
            "keyStrokeInfo": "\r\n\t\t",
            "position": "10,13"
        },
        {
            "operation": "TYPED",
            "lines": 0,
            "keyStrokeTimeStamp": "Tue Jul 13 2021 15:21:25",
            "keyStrokeInfo": "r",
            "position": "11,3"
        },
        {
            "operation": "TYPED",
            "lines": 0,
            "keyStrokeTimeStamp": "Tue Jul 13 2021 15:21:25",
            "keyStrokeInfo": "e",
            "position": "11,4"
        },
        {
            "operation": "TYPED",
            "lines": 0,
            "keyStrokeTimeStamp": "Tue Jul 13 2021 15:21:25",
            "keyStrokeInfo": "t",
            "position": "11,5"
        },
        {
            "operation": "TYPED",
            "lines": 0,
            "keyStrokeTimeStamp": "Tue Jul 13 2021 15:21:25",
            "keyStrokeInfo": "u",
            "position": "11,6"
        },
        {
            "operation": "TYPED",
            "lines": 0,
            "keyStrokeTimeStamp": "Tue Jul 13 2021 15:21:25",
            "keyStrokeInfo": "r",
            "position": "11,7"
        },
        {
            "operation": "TYPED",
            "lines": 0,
            "keyStrokeTimeStamp": "Tue Jul 13 2021 15:21:26",
            "keyStrokeInfo": "n",
            "position": "11,8"
        },
        {
            "operation": "TYPED",
            "lines": 0,
            "keyStrokeTimeStamp": "Tue Jul 13 2021 15:21:26",
            "keyStrokeInfo": " ",
            "position": "11,9"
        },
        {
            "operation": "TYPED",
            "lines": 0,
            "keyStrokeTimeStamp": "Tue Jul 13 2021 15:21:28",
            "keyStrokeInfo": "0",
            "position": "11,10"
        },
        {
            "operation": "TYPED",
            "lines": 0,
            "keyStrokeTimeStamp": "Tue Jul 13 2021 15:22:07",
            "keyStrokeInfo": "\r\n\t",
            "position": "9,16"
        },
        {
            "operation": "TYPED",
            "lines": 0,
            "keyStrokeTimeStamp": "Tue Jul 13 2021 15:22:08",
            "keyStrokeInfo": "c",
            "position": "10,2"
        },
        {
            "operation": "TYPED",
            "lines": 0,
            "keyStrokeTimeStamp": "Tue Jul 13 2021 15:22:08",
            "keyStrokeInfo": "a",
            "position": "10,3"
        },
        {
            "operation": "TYPED",
            "lines": 0,
            "keyStrokeTimeStamp": "Tue Jul 13 2021 15:22:08",
            "keyStrokeInfo": "r",
            "position": "10,4"
        },
        {
            "operation": "TYPED",
            "lines": 0,
            "keyStrokeTimeStamp": "Tue Jul 13 2021 15:22:09",
            "keyStrokeInfo": "t",
            "position": "10,5"
        },
        {
            "operation": "TYPED",
            "lines": 0,
            "keyStrokeTimeStamp": "Tue Jul 13 2021 15:22:10",
            "keyStrokeInfo": "o",
            "position": "10,6"
        },
        {
            "operation": "TYPED",
            "lines": 0,
            "keyStrokeTimeStamp": "Tue Jul 13 2021 15:22:10",
            "keyStrokeInfo": "n",
            "position": "10,7"
        },
        {
            "operation": "TYPED",
            "lines": 0,
            "keyStrokeTimeStamp": "Tue Jul 13 2021 15:22:11",
            "keyStrokeInfo": " ",
            "position": "10,8"
        },
        {
            "operation": "TYPED",
            "lines": 0,
            "keyStrokeTimeStamp": "Tue Jul 13 2021 15:22:11",
            "keyStrokeInfo": "=",
            "position": "10,9"
        },
        {
            "operation": "TYPED",
            "lines": 0,
            "keyStrokeTimeStamp": "Tue Jul 13 2021 15:22:11",
            "keyStrokeInfo": " ",
            "position": "10,10"
        },
        {
            "operation": "TYPED",
            "lines": 0,
            "keyStrokeTimeStamp": "Tue Jul 13 2021 15:22:13",
            "keyStrokeInfo": "e",
            "position": "10,11"
        },
        {
            "operation": "TYPED",
            "lines": 0,
            "keyStrokeTimeStamp": "Tue Jul 13 2021 15:22:13",
            "keyStrokeInfo": "g",
            "position": "10,12"
        },
        {
            "operation": "TYPED",
            "lines": 0,
            "keyStrokeTimeStamp": "Tue Jul 13 2021 15:22:13",
            "keyStrokeInfo": "g",
            "position": "10,13"
        },
        {
            "operation": "TYPED",
            "lines": 0,
            "keyStrokeTimeStamp": "Tue Jul 13 2021 15:22:14",
            "keyStrokeInfo": "s",
            "position": "10,14"
        },
        {
            "operation": "TYPED",
            "lines": 0,
            "keyStrokeTimeStamp": "Tue Jul 13 2021 15:22:14",
            "keyStrokeInfo": "/",
            "position": "10,15"
        },
        {
            "operation": "TYPED",
            "lines": 0,
            "keyStrokeTimeStamp": "Tue Jul 13 2021 15:22:15",
            "keyStrokeInfo": "1",
            "position": "10,16"
        },
        {
            "operation": "TYPED",
            "lines": 0,
            "keyStrokeTimeStamp": "Tue Jul 13 2021 15:22:15",
            "keyStrokeInfo": "2",
            "position": "10,17"
        },
        {
            "operation": "PASTE",
            "lines": 1,
            "keyStrokeTimeStamp": "Tue Jul 13 2021 15:23:03",
            "keyStrokeInfo": "# ",
            "position": "18,2"
        },
        {
            "operation": "TYPED",
            "lines": 0,
            "keyStrokeTimeStamp": "Tue Jul 13 2021 15:23:15",
            "keyStrokeInfo": "\\",
            "position": "12,11"
        },
        {
            "operation": "DELETE",
            "lines": 0,
            "keyStrokeTimeStamp": "Tue Jul 13 2021 15:23:16",
            "keyStrokeInfo": "",
            "position": "12,11"
        },
        {
            "operation": "TYPED",
            "lines": 0,
            "keyStrokeTimeStamp": "Tue Jul 13 2021 15:23:16",
            "keyStrokeInfo": "\r\n\t\t",
            "position": "12,11"
        },
        {
            "operation": "DELETE",
            "lines": 0,
            "keyStrokeTimeStamp": "Tue Jul 13 2021 15:23:17",
            "keyStrokeInfo": "",
            "position": "13,2"
        },
        {
            "operation": "TYPED",
            "lines": 0,
            "keyStrokeTimeStamp": "Tue Jul 13 2021 15:23:18",
            "keyStrokeInfo": "a",
            "position": "13,2"
        },
        {
            "operation": "TYPED",
            "lines": 0,
            "keyStrokeTimeStamp": "Tue Jul 13 2021 15:23:19",
            "keyStrokeInfo": "=",
            "position": "13,3"
        },
        {
            "operation": "TYPED",
            "lines": 0,
            "keyStrokeTimeStamp": "Tue Jul 13 2021 15:23:19",
            "keyStrokeInfo": " ",
            "position": "13,4"
        },
        {
            "operation": "TYPED",
            "lines": 0,
            "keyStrokeTimeStamp": "Tue Jul 13 2021 15:23:19",
            "keyStrokeInfo": "i",
            "position": "13,5"
        },
        {
            "operation": "TYPED",
            "lines": 0,
            "keyStrokeTimeStamp": "Tue Jul 13 2021 15:23:20",
            "keyStrokeInfo": "n",
            "position": "13,6"
        },
        {
            "operation": "TYPED",
            "lines": 0,
            "keyStrokeTimeStamp": "Tue Jul 13 2021 15:23:20",
            "keyStrokeInfo": "t",
            "position": "13,7"
        },
        {
            "operation": "TYPED",
            "lines": 0,
            "keyStrokeTimeStamp": "Tue Jul 13 2021 15:23:20",
            "keyStrokeInfo": "()",
            "position": "13,8"
        },
        {
            "operation": "TYPED",
            "lines": 0,
            "keyStrokeTimeStamp": "Tue Jul 13 2021 15:23:21",
            "keyStrokeInfo": "c",
            "position": "13,9"
        },
        {
            "operation": "TYPED",
            "lines": 0,
            "keyStrokeTimeStamp": "Tue Jul 13 2021 15:23:21",
            "keyStrokeInfo": "a",
            "position": "13,10"
        },
        {
            "operation": "TYPED",
            "lines": 0,
            "keyStrokeTimeStamp": "Tue Jul 13 2021 15:23:21",
            "keyStrokeInfo": "r",
            "position": "13,11"
        },
        {
            "operation": "TYPED",
            "lines": 0,
            "keyStrokeTimeStamp": "Tue Jul 13 2021 15:23:22",
            "keyStrokeInfo": "t",
            "position": "13,12"
        },
        {
            "operation": "TYPED",
            "lines": 0,
            "keyStrokeTimeStamp": "Tue Jul 13 2021 15:23:22",
            "keyStrokeInfo": "i",
            "position": "13,13"
        },
        {
            "operation": "DELETE",
            "lines": 0,
            "keyStrokeTimeStamp": "Tue Jul 13 2021 15:23:22",
            "keyStrokeInfo": "",
            "position": "13,13"
        },
        {
            "operation": "TYPED",
            "lines": 0,
            "keyStrokeTimeStamp": "Tue Jul 13 2021 15:23:23",
            "keyStrokeInfo": "o",
            "position": "13,13"
        },
        {
            "operation": "TYPED",
            "lines": 0,
            "keyStrokeTimeStamp": "Tue Jul 13 2021 15:23:23",
            "keyStrokeInfo": "n",
            "position": "13,14"
        },
        {
            "operation": "TYPED",
            "lines": 0,
            "keyStrokeTimeStamp": "Tue Jul 13 2021 15:23:24",
            "keyStrokeInfo": "\r\n\t",
            "position": "13,16"
        },
        {
            "operation": "TYPED",
            "lines": 0,
            "keyStrokeTimeStamp": "Tue Jul 13 2021 15:23:28",
            "keyStrokeInfo": "i",
            "position": "14,2"
        },
        {
            "operation": "TYPED",
            "lines": 0,
            "keyStrokeTimeStamp": "Tue Jul 13 2021 15:23:28",
            "keyStrokeInfo": "f",
            "position": "14,3"
        },
        {
            "operation": "TYPED",
            "lines": 0,
            "keyStrokeTimeStamp": "Tue Jul 13 2021 15:23:28",
            "keyStrokeInfo": " ",
            "position": "14,4"
        },
        {
            "operation": "TYPED",
            "lines": 0,
            "keyStrokeTimeStamp": "Tue Jul 13 2021 15:23:29",
            "keyStrokeInfo": "()",
            "position": "14,5"
        },
        {
            "operation": "TYPED",
            "lines": 0,
            "keyStrokeTimeStamp": "Tue Jul 13 2021 15:23:29",
            "keyStrokeInfo": "c",
            "position": "14,6"
        },
        {
            "operation": "TYPED",
            "lines": 0,
            "keyStrokeTimeStamp": "Tue Jul 13 2021 15:23:29",
            "keyStrokeInfo": "a",
            "position": "14,7"
        },
        {
            "operation": "TYPED",
            "lines": 0,
            "keyStrokeTimeStamp": "Tue Jul 13 2021 15:23:29",
            "keyStrokeInfo": "r",
            "position": "14,8"
        },
        {
            "operation": "TYPED",
            "lines": 0,
            "keyStrokeTimeStamp": "Tue Jul 13 2021 15:23:29",
            "keyStrokeInfo": "t",
            "position": "14,9"
        },
        {
            "operation": "TYPED",
            "lines": 0,
            "keyStrokeTimeStamp": "Tue Jul 13 2021 15:23:30",
            "keyStrokeInfo": "o",
            "position": "14,10"
        },
        {
            "operation": "TYPED",
            "lines": 0,
            "keyStrokeTimeStamp": "Tue Jul 13 2021 15:23:30",
            "keyStrokeInfo": "n",
            "position": "14,11"
        },
        {
            "operation": "TYPED",
            "lines": 0,
            "keyStrokeTimeStamp": "Tue Jul 13 2021 15:23:31",
            "keyStrokeInfo": " ",
            "position": "14,12"
        },
        {
            "operation": "TYPED",
            "lines": 0,
            "keyStrokeTimeStamp": "Tue Jul 13 2021 15:23:31",
            "keyStrokeInfo": ">",
            "position": "14,13"
        },
        {
            "operation": "TYPED",
            "lines": 0,
            "keyStrokeTimeStamp": "Tue Jul 13 2021 15:23:32",
            "keyStrokeInfo": "a",
            "position": "14,14"
        },
        {
            "operation": "TYPED",
            "lines": 0,
            "keyStrokeTimeStamp": "Tue Jul 13 2021 15:23:34",
            "keyStrokeInfo": ":",
            "position": "14,16"
        },
        {
            "operation": "TYPED",
            "lines": 0,
            "keyStrokeTimeStamp": "Tue Jul 13 2021 15:23:34",
            "keyStrokeInfo": "\r\n\t\t",
            "position": "14,17"
        },
        {
            "operation": "TYPED",
            "lines": 0,
            "keyStrokeTimeStamp": "Tue Jul 13 2021 15:23:35",
            "keyStrokeInfo": "r",
            "position": "15,3"
        },
        {
            "operation": "TYPED",
            "lines": 0,
            "keyStrokeTimeStamp": "Tue Jul 13 2021 15:23:35",
            "keyStrokeInfo": "e",
            "position": "15,4"
        },
        {
            "operation": "TYPED",
            "lines": 0,
            "keyStrokeTimeStamp": "Tue Jul 13 2021 15:23:35",
            "keyStrokeInfo": "t",
            "position": "15,5"
        },
        {
            "operation": "TYPED",
            "lines": 0,
            "keyStrokeTimeStamp": "Tue Jul 13 2021 15:23:35",
            "keyStrokeInfo": "u",
            "position": "15,6"
        },
        {
            "operation": "TYPED",
            "lines": 0,
            "keyStrokeTimeStamp": "Tue Jul 13 2021 15:23:35",
            "keyStrokeInfo": "r",
            "position": "15,7"
        },
        {
            "operation": "TYPED",
            "lines": 0,
            "keyStrokeTimeStamp": "Tue Jul 13 2021 15:23:36",
            "keyStrokeInfo": "n",
            "position": "15,8"
        },
        {
            "operation": "TYPED",
            "lines": 0,
            "keyStrokeTimeStamp": "Tue Jul 13 2021 15:23:36",
            "keyStrokeInfo": " ",
            "position": "15,9"
        },
        {
            "operation": "DELETE",
            "lines": 0,
            "keyStrokeTimeStamp": "Tue Jul 13 2021 15:23:42",
            "keyStrokeInfo": "",
            "position": "15,9"
        },
        {
            "operation": "DELETE",
            "lines": 0,
            "keyStrokeTimeStamp": "Tue Jul 13 2021 15:23:42",
            "keyStrokeInfo": "",
            "position": "15,8"
        },
        {
            "operation": "DELETE",
            "lines": 0,
            "keyStrokeTimeStamp": "Tue Jul 13 2021 15:23:42",
            "keyStrokeInfo": "",
            "position": "15,7"
        },
        {
            "operation": "DELETE",
            "lines": 0,
            "keyStrokeTimeStamp": "Tue Jul 13 2021 15:23:42",
            "keyStrokeInfo": "",
            "position": "15,6"
        },
        {
            "operation": "DELETE",
            "lines": 0,
            "keyStrokeTimeStamp": "Tue Jul 13 2021 15:23:42",
            "keyStrokeInfo": "",
            "position": "15,5"
        },
        {
            "operation": "DELETE",
            "lines": 0,
            "keyStrokeTimeStamp": "Tue Jul 13 2021 15:23:42",
            "keyStrokeInfo": "",
            "position": "15,4"
        },
        {
            "operation": "DELETE",
            "lines": 0,
            "keyStrokeTimeStamp": "Tue Jul 13 2021 15:23:43",
            "keyStrokeInfo": "",
            "position": "15,3"
        },
        {
            "operation": "TYPED",
            "lines": 0,
            "keyStrokeTimeStamp": "Tue Jul 13 2021 15:23:43",
            "keyStrokeInfo": "a",
            "position": "15,3"
        },
        {
            "operation": "TYPED",
            "lines": 0,
            "keyStrokeTimeStamp": "Tue Jul 13 2021 15:23:44",
            "keyStrokeInfo": "+",
            "position": "15,4"
        },
        {
            "operation": "TYPED",
            "lines": 0,
            "keyStrokeTimeStamp": "Tue Jul 13 2021 15:23:44",
            "keyStrokeInfo": "=",
            "position": "15,5"
        },
        {
            "operation": "TYPED",
            "lines": 0,
            "keyStrokeTimeStamp": "Tue Jul 13 2021 15:23:47",
            "keyStrokeInfo": "1",
            "position": "15,6"
        },
        {
            "operation": "TYPED",
            "lines": 0,
            "keyStrokeTimeStamp": "Tue Jul 13 2021 15:23:48",
            "keyStrokeInfo": "\r\n\t\t",
            "position": "15,7"
        },
        {
            "operation": "TYPED",
            "lines": 0,
            "keyStrokeTimeStamp": "Tue Jul 13 2021 15:23:51",
            "keyStrokeInfo": "r",
            "position": "16,3"
        },
        {
            "operation": "TYPED",
            "lines": 0,
            "keyStrokeTimeStamp": "Tue Jul 13 2021 15:23:51",
            "keyStrokeInfo": "e",
            "position": "16,4"
        },
        {
            "operation": "TYPED",
            "lines": 0,
            "keyStrokeTimeStamp": "Tue Jul 13 2021 15:23:51",
            "keyStrokeInfo": "t",
            "position": "16,5"
        },
        {
            "operation": "TYPED",
            "lines": 0,
            "keyStrokeTimeStamp": "Tue Jul 13 2021 15:23:51",
            "keyStrokeInfo": "u",
            "position": "16,6"
        },
        {
            "operation": "TYPED",
            "lines": 0,
            "keyStrokeTimeStamp": "Tue Jul 13 2021 15:23:51",
            "keyStrokeInfo": "r",
            "position": "16,7"
        },
        {
            "operation": "TYPED",
            "lines": 0,
            "keyStrokeTimeStamp": "Tue Jul 13 2021 15:23:51",
            "keyStrokeInfo": "n",
            "position": "16,8"
        },
        {
            "operation": "TYPED",
            "lines": 0,
            "keyStrokeTimeStamp": "Tue Jul 13 2021 15:23:51",
            "keyStrokeInfo": " ",
            "position": "16,9"
        },
        {
            "operation": "TYPED",
            "lines": 0,
            "keyStrokeTimeStamp": "Tue Jul 13 2021 15:23:52",
            "keyStrokeInfo": "a",
            "position": "16,10"
        },
        {
            "operation": "TYPED",
            "lines": 0,
            "keyStrokeTimeStamp": "Tue Jul 13 2021 15:23:52",
            "keyStrokeInfo": "a",
            "position": "16,10"
        },
        {
            "operation": "DELETE",
            "lines": 0,
            "keyStrokeTimeStamp": "Tue Jul 13 2021 15:23:52",
            "keyStrokeInfo": "",
            "position": "16,10"
        },
        {
            "operation": "TYPED",
            "lines": 0,
            "keyStrokeTimeStamp": "Tue Jul 13 2021 15:23:53",
            "keyStrokeInfo": "a",
            "position": "16,10"
        },
        {
            "operation": "TYPED",
            "lines": 0,
            "keyStrokeTimeStamp": "Tue Jul 13 2021 15:23:54",
            "keyStrokeInfo": "a",
            "position": "16,10"
        },
        {
            "operation": "DELETE",
            "lines": 0,
            "keyStrokeTimeStamp": "Tue Jul 13 2021 15:23:54",
            "keyStrokeInfo": "",
            "position": "16,10"
        },
        {
            "operation": "TYPED",
            "lines": 0,
            "keyStrokeTimeStamp": "Tue Jul 13 2021 15:23:54",
            "keyStrokeInfo": "a",
            "position": "16,10"
        },
        {
            "operation": "TYPED",
            "lines": 0,
            "keyStrokeTimeStamp": "Tue Jul 13 2021 15:23:54",
            "keyStrokeInfo": "a",
            "position": "16,10"
        },
        {
            "operation": "TYPED",
            "lines": 0,
            "keyStrokeTimeStamp": "Tue Jul 13 2021 15:23:55",
            "keyStrokeInfo": "\r\n\t\t",
            "position": "16,11"
        },
        {
            "operation": "DELETE",
            "lines": 0,
            "keyStrokeTimeStamp": "Tue Jul 13 2021 15:23:55",
            "keyStrokeInfo": "",
            "position": "17,2"
        },
        {
            "operation": "TYPED",
            "lines": 0,
            "keyStrokeTimeStamp": "Tue Jul 13 2021 15:24:00",
            "keyStrokeInfo": "r",
            "position": "17,2"
        },
        {
            "operation": "TYPED",
            "lines": 0,
            "keyStrokeTimeStamp": "Tue Jul 13 2021 15:24:00",
            "keyStrokeInfo": "e",
            "position": "17,3"
        },
        {
            "operation": "TYPED",
            "lines": 0,
            "keyStrokeTimeStamp": "Tue Jul 13 2021 15:24:00",
            "keyStrokeInfo": "t",
            "position": "17,4"
        },
        {
            "operation": "TYPED",
            "lines": 0,
            "keyStrokeTimeStamp": "Tue Jul 13 2021 15:24:00",
            "keyStrokeInfo": "u",
            "position": "17,5"
        },
        {
            "operation": "TYPED",
            "lines": 0,
            "keyStrokeTimeStamp": "Tue Jul 13 2021 15:24:01",
            "keyStrokeInfo": "r",
            "position": "17,6"
        },
        {
            "operation": "TYPED",
            "lines": 0,
            "keyStrokeTimeStamp": "Tue Jul 13 2021 15:24:01",
            "keyStrokeInfo": "n",
            "position": "17,7"
        },
        {
            "operation": "TYPED",
            "lines": 0,
            "keyStrokeTimeStamp": "Tue Jul 13 2021 15:24:01",
            "keyStrokeInfo": " ",
            "position": "17,8"
        },
        {
            "operation": "TYPED",
            "lines": 0,
            "keyStrokeTimeStamp": "Tue Jul 13 2021 15:24:01",
            "keyStrokeInfo": "a",
            "position": "17,9"
        },
        {
            "operation": "TYPED",
            "lines": 0,
            "keyStrokeTimeStamp": "Tue Jul 13 2021 15:24:01",
            "keyStrokeInfo": " ",
            "position": "17,10"
        },
        {
            "operation": "TYPED",
            "lines": 0,
            "keyStrokeTimeStamp": "Tue Jul 13 2021 15:24:15",
            "keyStrokeInfo": "\r\n\t",
            "position": "10,18"
        },
        {
            "operation": "TYPED",
            "lines": 0,
            "keyStrokeTimeStamp": "Tue Jul 13 2021 15:24:16",
            "keyStrokeInfo": "p",
            "position": "11,2"
        },
        {
            "operation": "TYPED",
            "lines": 0,
            "keyStrokeTimeStamp": "Tue Jul 13 2021 15:24:16",
            "keyStrokeInfo": "r",
            "position": "11,3"
        },
        {
            "operation": "TYPED",
            "lines": 0,
            "keyStrokeTimeStamp": "Tue Jul 13 2021 15:24:16",
            "keyStrokeInfo": "i",
            "position": "11,4"
        },
        {
            "operation": "TYPED",
            "lines": 0,
            "keyStrokeTimeStamp": "Tue Jul 13 2021 15:24:17",
            "keyStrokeInfo": "n",
            "position": "11,5"
        },
        {
            "operation": "TYPED",
            "lines": 0,
            "keyStrokeTimeStamp": "Tue Jul 13 2021 15:24:17",
            "keyStrokeInfo": "t",
            "position": "11,6"
        },
        {
            "operation": "TYPED",
            "lines": 0,
            "keyStrokeTimeStamp": "Tue Jul 13 2021 15:24:18",
            "keyStrokeInfo": "()",
            "position": "11,7"
        },
        {
            "operation": "TYPED",
            "lines": 0,
            "keyStrokeTimeStamp": "Tue Jul 13 2021 15:24:19",
            "keyStrokeInfo": "a",
            "position": "11,8"
        },
        {
            "operation": "DELETE",
            "lines": 0,
            "keyStrokeTimeStamp": "Tue Jul 13 2021 15:24:19",
            "keyStrokeInfo": "",
            "position": "11,8"
        },
        {
            "operation": "TYPED",
            "lines": 0,
            "keyStrokeTimeStamp": "Tue Jul 13 2021 15:24:20",
            "keyStrokeInfo": "c",
            "position": "11,8"
        },
        {
            "operation": "TYPED",
            "lines": 0,
            "keyStrokeTimeStamp": "Tue Jul 13 2021 15:24:20",
            "keyStrokeInfo": "a",
            "position": "11,9"
        },
        {
            "operation": "TYPED",
            "lines": 0,
            "keyStrokeTimeStamp": "Tue Jul 13 2021 15:24:20",
            "keyStrokeInfo": "r",
            "position": "11,10"
        },
        {
            "operation": "TYPED",
            "lines": 0,
            "keyStrokeTimeStamp": "Tue Jul 13 2021 15:24:20",
            "keyStrokeInfo": "y",
            "position": "11,11"
        },
        {
            "operation": "DELETE",
            "lines": 0,
            "keyStrokeTimeStamp": "Tue Jul 13 2021 15:24:21",
            "keyStrokeInfo": "",
            "position": "11,11"
        },
        {
            "operation": "TYPED",
            "lines": 0,
            "keyStrokeTimeStamp": "Tue Jul 13 2021 15:24:21",
            "keyStrokeInfo": "t",
            "position": "11,11"
        },
        {
            "operation": "TYPED",
            "lines": 0,
            "keyStrokeTimeStamp": "Tue Jul 13 2021 15:24:21",
            "keyStrokeInfo": "i",
            "position": "11,12"
        },
        {
            "operation": "TYPED",
            "lines": 0,
            "keyStrokeTimeStamp": "Tue Jul 13 2021 15:24:21",
            "keyStrokeInfo": "n",
            "position": "11,13"
        },
        {
            "operation": "DELETE",
            "lines": 0,
            "keyStrokeTimeStamp": "Tue Jul 13 2021 15:24:22",
            "keyStrokeInfo": "",
            "position": "11,13"
        },
        {
            "operation": "DELETE",
            "lines": 0,
            "keyStrokeTimeStamp": "Tue Jul 13 2021 15:24:22",
            "keyStrokeInfo": "",
            "position": "11,12"
        },
        {
            "operation": "TYPED",
            "lines": 0,
            "keyStrokeTimeStamp": "Tue Jul 13 2021 15:24:22",
            "keyStrokeInfo": "o",
            "position": "11,12"
        },
        {
            "operation": "TYPED",
            "lines": 0,
            "keyStrokeTimeStamp": "Tue Jul 13 2021 15:24:22",
            "keyStrokeInfo": "n",
            "position": "11,13"
        },
        {
            "operation": "TYPED",
            "lines": 0,
            "keyStrokeTimeStamp": "Tue Jul 13 2021 15:24:24",
            "keyStrokeInfo": "\r\n\t",
            "position": "18,11"
        },
        {
            "operation": "DELETE",
            "lines": 0,
            "keyStrokeTimeStamp": "Tue Jul 13 2021 15:24:25",
            "keyStrokeInfo": "",
            "position": "19,1"
        },
        {
            "operation": "TYPED",
            "lines": 0,
            "keyStrokeTimeStamp": "Tue Jul 13 2021 15:24:27",
            "keyStrokeInfo": "f",
            "position": "19,1"
        },
        {
            "operation": "TYPED",
            "lines": 0,
            "keyStrokeTimeStamp": "Tue Jul 13 2021 15:24:27",
            "keyStrokeInfo": "u",
            "position": "19,2"
        },
        {
            "operation": "TYPED",
            "lines": 0,
            "keyStrokeTimeStamp": "Tue Jul 13 2021 15:24:28",
            "keyStrokeInfo": "n",
            "position": "19,3"
        },
        {
            "operation": "PASTE",
            "lines": 1,
            "keyStrokeTimeStamp": "Tue Jul 13 2021 15:24:28",
            "keyStrokeInfo": "fun_eggcartons",
            "position": "19,1"
        },
        {
            "operation": "TYPED",
            "lines": 0,
            "keyStrokeTimeStamp": "Tue Jul 13 2021 15:24:29",
            "keyStrokeInfo": "()",
            "position": "19,15"
        },
        {
            "operation": "TYPED",
            "lines": 0,
            "keyStrokeTimeStamp": "Tue Jul 13 2021 15:24:35",
            "keyStrokeInfo": "2",
            "position": "19,16"
        },
        {
            "operation": "TYPED",
            "lines": 0,
            "keyStrokeTimeStamp": "Tue Jul 13 2021 15:24:35",
            "keyStrokeInfo": "2",
            "position": "19,17"
        },
        {
            "operation": "TYPED",
            "lines": 0,
            "keyStrokeTimeStamp": "Tue Jul 13 2021 15:24:57",
            "keyStrokeInfo": "\r\n\t",
            "position": "14,16"
        },
        {
            "operation": "TYPED",
            "lines": 0,
            "keyStrokeTimeStamp": "Tue Jul 13 2021 15:24:58",
            "keyStrokeInfo": "p",
            "position": "15,2"
        },
        {
            "operation": "TYPED",
            "lines": 0,
            "keyStrokeTimeStamp": "Tue Jul 13 2021 15:24:58",
            "keyStrokeInfo": "r",
            "position": "15,3"
        },
        {
            "operation": "TYPED",
            "lines": 0,
            "keyStrokeTimeStamp": "Tue Jul 13 2021 15:24:58",
            "keyStrokeInfo": "i",
            "position": "15,4"
        },
        {
            "operation": "TYPED",
            "lines": 0,
            "keyStrokeTimeStamp": "Tue Jul 13 2021 15:24:59",
            "keyStrokeInfo": "n",
            "position": "15,5"
        },
        {
            "operation": "TYPED",
            "lines": 0,
            "keyStrokeTimeStamp": "Tue Jul 13 2021 15:24:59",
            "keyStrokeInfo": "t",
            "position": "15,6"
        },
        {
            "operation": "TYPED",
            "lines": 0,
            "keyStrokeTimeStamp": "Tue Jul 13 2021 15:25:00",
            "keyStrokeInfo": "()",
            "position": "15,7"
        },
        {
            "operation": "TYPED",
            "lines": 0,
            "keyStrokeTimeStamp": "Tue Jul 13 2021 15:25:00",
            "keyStrokeInfo": "a",
            "position": "15,8"
        },
        {
            "operation": "TYPED",
            "lines": 0,
            "keyStrokeTimeStamp": "Tue Jul 13 2021 15:25:26",
            "keyStrokeInfo": "\r\n\t\t",
            "position": "17,7"
        },
        {
            "operation": "TYPED",
            "lines": 0,
            "keyStrokeTimeStamp": "Tue Jul 13 2021 15:25:27",
            "keyStrokeInfo": "p",
            "position": "18,3"
        },
        {
            "operation": "TYPED",
            "lines": 0,
            "keyStrokeTimeStamp": "Tue Jul 13 2021 15:25:28",
            "keyStrokeInfo": "r",
            "position": "18,4"
        },
        {
            "operation": "TYPED",
            "lines": 0,
            "keyStrokeTimeStamp": "Tue Jul 13 2021 15:25:28",
            "keyStrokeInfo": "i",
            "position": "18,5"
        },
        {
            "operation": "TYPED",
            "lines": 0,
            "keyStrokeTimeStamp": "Tue Jul 13 2021 15:25:28",
            "keyStrokeInfo": "n",
            "position": "18,6"
        },
        {
            "operation": "TYPED",
            "lines": 0,
            "keyStrokeTimeStamp": "Tue Jul 13 2021 15:25:28",
            "keyStrokeInfo": "t",
            "position": "18,7"
        },
        {
            "operation": "TYPED",
            "lines": 0,
            "keyStrokeTimeStamp": "Tue Jul 13 2021 15:25:29",
            "keyStrokeInfo": "()",
            "position": "18,8"
        },
        {
            "operation": "TYPED",
            "lines": 0,
            "keyStrokeTimeStamp": "Tue Jul 13 2021 15:25:29",
            "keyStrokeInfo": "a",
            "position": "18,9"
        },
        {
            "operation": "TYPED",
            "lines": 0,
            "keyStrokeTimeStamp": "Tue Jul 13 2021 15:25:39",
            "keyStrokeInfo": " ",
            "position": "16,14"
        },
        {
            "operation": "TYPED",
            "lines": 0,
            "keyStrokeTimeStamp": "Tue Jul 13 2021 15:26:16",
            "keyStrokeInfo": "/",
            "position": "10,16"
        },
        {
            "operation": "DELETE",
            "lines": 0,
            "keyStrokeTimeStamp": "Tue Jul 13 2021 15:26:31",
            "keyStrokeInfo": "",
            "position": "10,16"
        },
        {
            "operation": "DELETE",
            "lines": 5,
            "keyStrokeTimeStamp": "Tue Jul 13 2021 15:26:49",
            "keyStrokeInfo": "",
            "position": "22,2"
        },
        {
            "operation": "TYPED",
            "lines": 0,
            "keyStrokeTimeStamp": "Tue Jul 13 2021 15:26:53",
            "keyStrokeInfo": "# ",
            "position": "21,1"
        },
        {
            "operation": "DELETE",
            "lines": 0,
            "keyStrokeTimeStamp": "Tue Jul 13 2021 15:27:01",
            "keyStrokeInfo": "",
            "position": "9,2"
        }
    ]
}